pyannoteai/sdk/__init__.py
pyannoteai/sdk/client.py
pyannoteai_sdk-0.3.0.dist-info/METADATA
pyannoteai_sdk-0.3.0.dist-info/WHEEL
pyannoteai_sdk-0.3.0.dist-info/licenses/LICENSE
pyannoteai_sdk-0.3.0.dist-info/RECORD
