Metadata-Version: 2.4
Name: pyannoteai-sdk
Version: 0.3.0
Summary: Official pyannoteAI Python SDK
Author-email: Hervé BREDIN <herve@pyannote.ai>
License-File: LICENSE
Requires-Python: >=3.10
Requires-Dist: requests>=2.32.3
